secat/EmpiricalBrownsMethod.py
secat/__init__.py
secat/learn.py
secat/main.py
secat/plot.py
secat/preprocess.py
secat/quantify.py
secat/score.py
secat-1.0.2.dist-info/LICENSE
secat-1.0.2.dist-info/METADATA
secat-1.0.2.dist-info/WHEEL
secat-1.0.2.dist-info/entry_points.txt
secat-1.0.2.dist-info/top_level.txt
secat-1.0.2.dist-info/RECORD
