Metadata-Version: 2.1
Name: secat
Version: 1.0.2
Summary: Size-Exclusion Chromatography Algorithmic Toolkit
Home-page: https://github.com/grosenberger/secat
Author: George Rosenberger
Author-email: gr2578@cumc.columbia.edu
License: UNKNOWN
Platform: UNKNOWN
Classifier: Development Status :: 3 - Alpha
Classifier: License :: OSI Approved :: BSD License
Classifier: Operating System :: OS Independent
Classifier: Environment :: Console
Classifier: Intended Audience :: Science/Research
Classifier: Topic :: Scientific/Engineering :: Bio-Informatics
Classifier: Topic :: Scientific/Engineering :: Chemistry
Classifier: Programming Language :: Python :: 3
Classifier: Programming Language :: Python :: 3.4
Classifier: Programming Language :: Python :: 3.5
Classifier: Programming Language :: Python :: 3.6
Classifier: Programming Language :: Python :: 3.7
Requires-Dist: Click
Requires-Dist: tqdm
Requires-Dist: tzlocal
Requires-Dist: lxml
Requires-Dist: numpy
Requires-Dist: scipy
Requires-Dist: pandas
Requires-Dist: sklearn
Requires-Dist: pyprophet
Requires-Dist: minepy
Requires-Dist: rpy2
Requires-Dist: matplotlib
